ezrendr/__init__.py
ezrendr/cli.py
ezrendr-0.0.0.dist-info/LICENSE
ezrendr-0.0.0.dist-info/METADATA
ezrendr-0.0.0.dist-info/WHEEL
ezrendr-0.0.0.dist-info/top_level.txt
ezrendr-0.0.0.dist-info/RECORD
