Metadata-Version: 2.1
Name: ezrendr
Version: 0.0.0
Summary: ezrendr library
Home-page: 
Author: ezrendr.com
License: UNKNOWN
Platform: UNKNOWN
License-File: LICENSE
Requires-Dist: requirements.txt
